<?xml version="1.0" encoding="utf-8"?>
<DoorAccessList xmlns:xsi="http://www.w3.org/2001/XMLSchema-instance" xmlns:xsd="http://www.w3.org/2001/XMLSchema">
  <DoorAccessDevices DevId="f92cba41-43a0-4e95-9ec8-3804aefcb7b6" TypeCode="0" Name="集控楼0米联氨储存间" ParentName="集控楼0m层|集控楼" ParentId="0" ModelName="其他_单联单控开关_3D" KKSCode="" Abutment_DevID="0x006F95AB1705DC824349A5655CD77955CC48" XPos="49.4783" YPos="1.77372" ZPos="6.7685" RotationX="2.60551E-11" RotationY="270" RotationZ="-0.000159599" ScaleX="1" ScaleY="1" ScaleZ="1" DoorId="6" Local_DevId="f92cba41-43a0-4e95-9ec8-3804aefcb7b6" />
  <DoorAccessDevices DevId="4afe2652-0dff-4081-9072-a92e45ba2bac" TypeCode="0" Name="集控楼0米化学加药间" ParentName="集控楼0m层|集控楼" ParentId="0" ModelName="其他_单联单控开关_3D" KKSCode="" Abutment_DevID="0x006F03F2A98CB53C4AA5AAC3DC133CF25AB8" XPos="43.9882" YPos="1.77372" ZPos="10.9714" RotationX="0.000159599" RotationY="0" RotationZ="0" ScaleX="1" ScaleY="1" ScaleZ="1" DoorId="7" Local_DevId="4afe2652-0dff-4081-9072-a92e45ba2bac" />
  <DoorAccessDevices DevId="28a3d1ec-7c98-459f-8db4-ced87beb8883" TypeCode="0" Name="集控楼0米柴油发电机房(兼巡更)" ParentName="集控楼0m层|集控楼" ParentId="0" ModelName="其他_单联单控开关_3D" KKSCode="" Abutment_DevID="0x006F9E5CC341672943B3B0884397BFA971D6" XPos="33.6499" YPos="1.72304" ZPos="23.6813" RotationX="0.000159599" RotationY="0" RotationZ="0" ScaleX="1" ScaleY="1" ScaleZ="1" DoorId="11" Local_DevId="28a3d1ec-7c98-459f-8db4-ced87beb8883" />
  <DoorAccessDevices DevId="02f54aee-d426-4b8b-a160-186f4ddc5b74" TypeCode="0" Name="集控楼0米机房备件间" ParentName="集控楼0m层|集控楼" ParentId="0" ModelName="其他_单联单控开关_3D" KKSCode="" Abutment_DevID="0x006F9F443DBE75904168950E1A9BCA425E05" XPos="33.481" YPos="1.75682" ZPos="12.6255" RotationX="-0.000152769" RotationY="180" RotationZ="-1.33555E-11" ScaleX="1" ScaleY="1" ScaleZ="1" DoorId="3" Local_DevId="02f54aee-d426-4b8b-a160-186f4ddc5b74" />
  <DoorAccessDevices DevId="2773624f-a1dd-4e4f-8953-bb1bc685066f" TypeCode="0" Name="集控楼0米2号油箱间(兼巡更)" ParentName="集控楼0m层|集控楼" ParentId="0" ModelName="其他_单联单控开关_3D" KKSCode="" Abutment_DevID="0x006F3511D51884534908AA4F708444A58DEF" XPos="31.5553" YPos="1.46965" ZPos="23.6813" RotationX="0.000159599" RotationY="0" RotationZ="0" ScaleX="1" ScaleY="1" ScaleZ="1" DoorId="12" Local_DevId="2773624f-a1dd-4e4f-8953-bb1bc685066f" />
  <DoorAccessDevices DevId="82f9105c-eca4-4a1e-aa17-21280d713856" TypeCode="0" Name="集控楼0米1号油箱间" ParentName="集控楼0m层|集控楼" ParentId="0" ModelName="其他_单联单控开关_3D" KKSCode="" Abutment_DevID="0x006FF3A783B6C8DD4766B81BDE01F5BCC45F" XPos="27.3828" YPos="1.46965" ZPos="23.6813" RotationX="0.000159599" RotationY="0" RotationZ="0" ScaleX="1" ScaleY="1" ScaleZ="1" DoorId="13" Local_DevId="82f9105c-eca4-4a1e-aa17-21280d713856" />
  <DoorAccessDevices DevId="67d40965-8eae-4a3c-b126-bb60faa00dc1" TypeCode="0" Name="集控楼0米电子设备间2号门" ParentName="集控楼0m层|集控楼" ParentId="0" ModelName="其他_单联单控开关_3D" KKSCode="" Abutment_DevID="0x006FF7B9DA76743C49CFB271A0949430DDEB" XPos="31.7749" YPos="1.77372" ZPos="10.6169" RotationX="0.000159599" RotationY="0" RotationZ="0" ScaleX="1" ScaleY="1" ScaleZ="1" DoorId="1" Local_DevId="67d40965-8eae-4a3c-b126-bb60faa00dc1" />
  <DoorAccessDevices DevId="07cf96c8-2007-42e4-92df-b2e8005c032e" TypeCode="0" Name="集控楼0米电子设备间1号门(兼巡更)" ParentName="集控楼0m层|集控楼" ParentId="0" ModelName="其他_单联单控开关_3D" KKSCode="" Abutment_DevID="0x006F15A5357E3ED04993BB9E32013A7721A8" XPos="18.2608" YPos="1.75682" ZPos="10.6169" RotationX="0.000159599" RotationY="0" RotationZ="0" ScaleX="1" ScaleY="1" ScaleZ="1" DoorId="0" Local_DevId="07cf96c8-2007-42e4-92df-b2e8005c032e" />
  <DoorAccessDevices DevId="52b4a61d-74aa-4bff-ac7c-17b64ef72c82" TypeCode="0" Name="集控楼0米电子设备间3号门(兼巡更)" ParentName="集控楼0m层|集控楼" ParentId="0" ModelName="其他_单联单控开关_3D" KKSCode="" Abutment_DevID="0x006FC06D36A78A734C3DAFCF6A307DD26DB3" XPos="9.18954" YPos="1.60479" ZPos="-0.0168791" RotationX="-0.000159599" RotationY="180" RotationZ="-1.39526E-11" ScaleX="1" ScaleY="1" ScaleZ="1" DoorId="19" Local_DevId="52b4a61d-74aa-4bff-ac7c-17b64ef72c82" />
  <DoorAccessDevices DevId="fc5b5a87-e650-49ba-8c24-28a913347edd" TypeCode="0" Name="集控楼0米1号空调机房" ParentName="集控楼0m层|集控楼" ParentId="0" ModelName="其他_单联单控开关_3D" KKSCode="" Abutment_DevID="0x006F5BE97AA2E27E4FF5B5F4D89AC3FEB212" XPos="25.2037" YPos="1.60479" ZPos="23.6813" RotationX="0.000159599" RotationY="0" RotationZ="0" ScaleX="1" ScaleY="1" ScaleZ="1" DoorId="14" Local_DevId="fc5b5a87-e650-49ba-8c24-28a913347edd" />
  <DoorAccessDevices DevId="cbbe14d9-ac8f-4808-8d2e-5f1f2de56262" TypeCode="0" Name="集控楼0米工作段配电室1号门" ParentName="集控楼0m层|集控楼" ParentId="0" ModelName="其他_单联单控开关_3D" KKSCode="" Abutment_DevID="0x006FE29705ED86A3492E8EA0A8B736D91BA2" XPos="14.4093" YPos="1.75682" ZPos="14.9042" RotationX="1.30276E-11" RotationY="90" RotationZ="0.000159599" ScaleX="1" ScaleY="1" ScaleZ="1" DoorId="4" Local_DevId="cbbe14d9-ac8f-4808-8d2e-5f1f2de56262" />
  <DoorAccessDevices DevId="2285eab9-e638-4545-8919-23efdde4de93" TypeCode="0" Name="集控楼0米工作段配电室2号门" ParentName="集控楼0m层|集控楼" ParentId="0" ModelName="其他_单联单控开关_3D" KKSCode="" Abutment_DevID="0x006F73BF4941D6A44ACFA9C10D0A983ADB9A" XPos="5.32115" YPos="1.60479" ZPos="23.6813" RotationX="0.000159599" RotationY="0" RotationZ="0" ScaleX="1" ScaleY="1" ScaleZ="1" DoorId="16" Local_DevId="2285eab9-e638-4545-8919-23efdde4de93" />
  <DoorAccessDevices DevId="a970d3d5-3a4e-4be9-8b68-2a00b0079a9a" TypeCode="0" Name="集控楼0米2号空调机房" ParentName="集控楼0m层|集控楼" ParentId="0" ModelName="其他_单联单控开关_3D" KKSCode="" Abutment_DevID="" XPos="3.46297" YPos="1.60479" ZPos="-0.0168791" RotationX="-0.000159599" RotationY="180" RotationZ="-1.39526E-11" ScaleX="1" ScaleY="1" ScaleZ="1" DoorId="18" Local_DevId="a970d3d5-3a4e-4be9-8b68-2a00b0079a9a" />
  <DoorAccessDevices DevId="82fe650a-9be1-4a71-ac75-3473844ba217" TypeCode="0" Name="集控楼4.5米高温架间(兼巡更)" ParentName="集控楼4.5m层|集控楼" ParentId="0" ModelName="其他_单联单控开关_3D" KKSCode="" Abutment_DevID="0x006F57368455A3BA46568020514841F8FE50" XPos="46.6572" YPos="1.77372" ZPos="4.28728" RotationX="0.00020058" RotationY="0" RotationZ="-7.27971E-19" ScaleX="1" ScaleY="1" ScaleZ="1" DoorId="16" Local_DevId="82fe650a-9be1-4a71-ac75-3473844ba217" />
  <DoorAccessDevices DevId="83747337-5cf8-4c70-8989-aed2adca70a2" TypeCode="0" Name="集控楼4.5米仪表盘间（兼巡更）" ParentName="集控楼4.5m层|集控楼" ParentId="0" ModelName="其他_单联单控开关_3D" KKSCode="" Abutment_DevID="0x006F08A5D0C73ED84B79902610D3C4297D18" XPos="45.6099" YPos="1.77372" ZPos="10.9714" RotationX="0.000227901" RotationY="0" RotationZ="-7.27971E-19" ScaleX="1" ScaleY="1" ScaleZ="1" DoorId="11" Local_DevId="83747337-5cf8-4c70-8989-aed2adca70a2" />
  <DoorAccessDevices DevId="06ccdb7a-f827-4f44-a9ad-d1d1af7de872" TypeCode="0" Name="集控楼4.5米会议室" ParentName="集控楼4.5m层|集控楼" ParentId="0" ModelName="其他_单联单控开关_3D" KKSCode="0x006F8CF7A382122E4FC5B3740CC877698B5D" Abutment_DevID="" XPos="35.8122" YPos="6.3347" ZPos="1.77372" RotationX="-0.000227901" RotationY="180" RotationZ="-1.99237E-11" ScaleX="1" ScaleY="1" ScaleZ="1" DoorId="9" Local_DevId="06ccdb7a-f827-4f44-a9ad-d1d1af7de872" />
  <DoorAccessDevices DevId="9a633a97-6127-44db-b715-561092887080" TypeCode="0" Name="集控楼4.5米线缆夹层" ParentName="集控楼4.5m层|集控楼" ParentId="0" ModelName="其他_单联单控开关_3D" KKSCode="" Abutment_DevID="0x006F39F0D13809B34D44B9BBF3EA5EA9A79D" XPos="30.2377" YPos="1.77372" ZPos="10.9545" RotationX="0.00020058" RotationY="0" RotationZ="-7.27971E-19" ScaleX="1" ScaleY="1" ScaleZ="1" DoorId="8" Local_DevId="9a633a97-6127-44db-b715-561092887080" />
  <DoorAccessDevices DevId="6d3e88ec-f66c-41eb-9213-6f9df75c63b4" TypeCode="0" Name="集控楼4.5米工程师室" ParentName="集控楼4.5m层|集控楼" ParentId="0" ModelName="其他_单联单控开关_3D" KKSCode="" Abutment_DevID="0x006FC8954232F54641C3B036D87D4F79D9BF" XPos="29.3086" YPos="1.77372" ZPos="12.6424" RotationX="-0.000262052" RotationY="180" RotationZ="-2.29093E-11" ScaleX="1" ScaleY="1" ScaleZ="1" DoorId="7" Local_DevId="6d3e88ec-f66c-41eb-9213-6f9df75c63b4" />
  <DoorAccessDevices DevId="3b6c0af7-92c1-4eb7-bff4-c03a204e9d67" TypeCode="0" Name="集控楼4.5米SIS室（兼巡更）" ParentName="集控楼4.5m层|集控楼" ParentId="0" ModelName="其他_单联单控开关_3D" KKSCode="" Abutment_DevID="0x006FAE18942A2C12448EA75C3BFA0470B233" XPos="25.1868" YPos="1.77372" ZPos="10.9714" RotationX="0.000262052" RotationY="0" RotationZ="4.85314E-20" ScaleX="1" ScaleY="1" ScaleZ="1" DoorId="6" Local_DevId="3b6c0af7-92c1-4eb7-bff4-c03a204e9d67" />
  <DoorAccessDevices DevId="2c3e1fab-c114-45bf-93ec-837d91684605" TypeCode="0" Name="集控楼4.5米集控室大门(右)" ParentName="集控楼4.5m层|集控楼" ParentId="0" ModelName="其他_单联单控开关_3D" KKSCode="" Abutment_DevID="0x006FF5B9BA6F68D64981B644FEB5A3886A32" XPos="18.7676" YPos="1.77372" ZPos="3.12262" RotationX="0" RotationY="90" RotationZ="0.000262052" ScaleX="1" ScaleY="1" ScaleZ="1" DoorId="20" Local_DevId="2c3e1fab-c114-45bf-93ec-837d91684605" />
  <DoorAccessDevices DevId="c8b92381-a5b3-426e-8210-e78234178b99" TypeCode="0" Name="集控楼4.5米集控室大门(左)" ParentName="集控楼4.5m层|集控楼" ParentId="0" ModelName="其他_单联单控开关_3D" KKSCode="" Abutment_DevID="0x006F1A5C20DDCB4F4D3D94F2C69B9DE71B7B" XPos="18.7676" YPos="1.77372" ZPos="18.7189" RotationX="0" RotationY="90" RotationZ="0.000262052" ScaleX="1" ScaleY="1" ScaleZ="1" DoorId="19" Local_DevId="c8b92381-a5b3-426e-8210-e78234178b99" />
  <DoorAccessDevices DevId="6d151bff-b7b0-4aa8-be67-d83157338fa0" TypeCode="0" Name="集控楼4.5米层集控室3号门" ParentName="集控楼4.5m层|集控楼" ParentId="0" ModelName="其他_单联单控开关_3D" KKSCode="" Abutment_DevID="0x006FEA9CC3126EEF4820BA7EEE0224DD15F2" XPos="4.40895" YPos="1.77372" ZPos="5.6376" RotationX="0" RotationY="270" RotationZ="-0.00020058" ScaleX="1" ScaleY="1" ScaleZ="1" DoorId="1" Local_DevId="6d151bff-b7b0-4aa8-be67-d83157338fa0" />
  <DoorAccessDevices DevId="141b3805-c939-4b25-8f98-7e8f8d079815" TypeCode="0" Name="集控楼8.8米备品间（兼巡更）" ParentName="集控楼8.8m层|集控楼" ParentId="0" ModelName="其他_单联单控开关_3D" KKSCode="" Abutment_DevID="0x006F0AA56EF8DA7D4C26B022CE2E12E5D8BD" XPos="38.363" YPos="1.77372" ZPos="10.9714" RotationX="0.00020058" RotationY="0" RotationZ="-7.27971E-19" ScaleX="1" ScaleY="1" ScaleZ="1" DoorId="12" Local_DevId="141b3805-c939-4b25-8f98-7e8f8d079815" />
  <DoorAccessDevices DevId="8def2949-7fcb-459f-91bd-64f0c3dfe2ae" TypeCode="0" Name="集控楼8.8米层蓄电池室" ParentName="集控楼8.8m层|集控楼" ParentId="0" ModelName="其他_单联单控开关_3D" KKSCode="" Abutment_DevID="0x006F807A3E279FF944AAAA4EA9CB6F704BD6" XPos="27.0281" YPos="1.77372" ZPos="10.9714" RotationX="0.00020058" RotationY="0" RotationZ="-7.27971E-19" ScaleX="1" ScaleY="1" ScaleZ="1" DoorId="7" Local_DevId="8def2949-7fcb-459f-91bd-64f0c3dfe2ae" />
  <DoorAccessDevices DevId="fec70603-1039-4737-a791-2998bb621964" TypeCode="0" Name="集控楼8.8米层会议室(304)" ParentName="集控楼8.8m层|集控楼" ParentId="0" ModelName="其他_单联单控开关_3D" KKSCode="" Abutment_DevID="0x006F89DDBFF3CD7D452AB96C5DECE4B08C4F" XPos="28.7173" YPos="1.77372" ZPos="12.6424" RotationX="-0.00020058" RotationY="180" RotationZ="-1.75353E-11" ScaleX="1" ScaleY="1" ScaleZ="1" DoorId="8" Local_DevId="fec70603-1039-4737-a791-2998bb621964" />
  <DoorAccessDevices DevId="7e130d7a-e5a7-4eb6-923a-7681beec7dd6" TypeCode="0" Name="集控楼8.8米层3号运行人员办公室" ParentName="集控楼8.8m层|集控楼" ParentId="0" ModelName="其他_单联单控开关_3D" KKSCode="" Abutment_DevID="0x006F5E0A0AC289114AE1B3FC2F3C13C7F0A3" XPos="23.6496" YPos="1.77372" ZPos="12.6424" RotationX="-0.00020058" RotationY="180" RotationZ="-1.75353E-11" ScaleX="1" ScaleY="1" ScaleZ="1" DoorId="6" Local_DevId="7e130d7a-e5a7-4eb6-923a-7681beec7dd6" />
  <DoorAccessDevices DevId="cd895274-d441-4620-b14f-8200c6dcf8f8" TypeCode="0" Name="集控楼8.8米2号运行人员办公室" ParentName="集控楼8.8m层|集控楼" ParentId="0" ModelName="其他_单联单控开关_3D" KKSCode="" Abutment_DevID="0x006F7DDD9CAD176F4EC9A5AC18738F3CE8A8" XPos="17.3317" YPos="1.77372" ZPos="12.6424" RotationX="-0.00020058" RotationY="180" RotationZ="-1.75353E-11" ScaleX="1" ScaleY="1" ScaleZ="1" DoorId="4" Local_DevId="cd895274-d441-4620-b14f-8200c6dcf8f8" />
  <DoorAccessDevices DevId="ae8b655a-0c8b-4837-b96a-7cf1e792ff84" TypeCode="0" Name="集控楼8.8米1号运行人员办公室" ParentName="集控楼8.8m层|集控楼" ParentId="0" ModelName="其他_单联单控开关_3D" KKSCode="" Abutment_DevID="0x006F77230C0A6EF1403196CE01D572672EF3" XPos="10.8112" YPos="1.77372" ZPos="12.6424" RotationX="-0.00020058" RotationY="180" RotationZ="-1.75353E-11" ScaleX="1" ScaleY="1" ScaleZ="1" DoorId="2" Local_DevId="ae8b655a-0c8b-4837-b96a-7cf1e792ff84" />
  <DoorAccessDevices DevId="85bc7872-39b3-447c-be8b-802710c18a92" TypeCode="0" Name="集控楼8.8米继电器室" ParentName="集控楼8.8m层|集控楼" ParentId="0" ModelName="其他_单联单控开关_3D" KKSCode="" Abutment_DevID="0x006FE0DA1FC091BB4AEDA0B33F4607DB50D4" XPos="10.3213" YPos="1.77372" ZPos="10.9545" RotationX="5.7146E-05" RotationY="0" RotationZ="4.85314E-20" ScaleX="1" ScaleY="1" ScaleZ="1" DoorId="3" Local_DevId="85bc7872-39b3-447c-be8b-802710c18a92" />
  <DoorAccessDevices DevId="a8ad9918-0dcf-4899-b506-6d9af00ca7c3" TypeCode="0" Name="集控楼8.8米空调机房（兼巡更）" ParentName="集控楼8.8m层|集控楼" ParentId="0" ModelName="其他_单联单控开关_3D" KKSCode="" Abutment_DevID="0x006FB41D1F4FA35542BEB027336139865B90" XPos="0.625024" YPos="1.77372" ZPos="10.9883" RotationX="0.000180089" RotationY="0" RotationZ="4.85314E-20" ScaleX="1" ScaleY="1" ScaleZ="1" DoorId="0" Local_DevId="a8ad9918-0dcf-4899-b506-6d9af00ca7c3" />
  <DoorAccessDevices DevId="3af62818-7352-4673-8825-81f9d11474ee" TypeCode="0" Name="集控楼13.1米1号会议室(兼巡更)" ParentName="集控楼13.1m层|集控楼" ParentId="0" ModelName="其他_单联单控开关_3D" KKSCode="" Abutment_DevID="0x006FEE0B7A438B50462AA7BDD4BF52F916DF" XPos="47.6708" YPos="1.77372" ZPos="10.9714" RotationX="0.000132278" RotationY="0" RotationZ="4.85314E-20" ScaleX="1" ScaleY="1" ScaleZ="1" DoorId="8" Local_DevId="3af62818-7352-4673-8825-81f9d11474ee" />
  <DoorAccessDevices DevId="3e7ed267-81db-4430-b1af-f30455feebf8" TypeCode="0" Name="集控楼13.1米4号运行人员办公室" ParentName="集控楼13.1m层|集控楼" ParentId="0" ModelName="其他_单联单控开关_3D" KKSCode="" Abutment_DevID="0x006F0BED60D7A84249D6B31E244D88C19328" XPos="49.4951" YPos="1.77372" ZPos="12.6424" RotationX="-0.000132278" RotationY="180" RotationZ="-1.15641E-11" ScaleX="1" ScaleY="1" ScaleZ="1" DoorId="7" Local_DevId="3e7ed267-81db-4430-b1af-f30455feebf8" />
  <DoorAccessDevices DevId="b9b19f92-9606-469f-923d-8b62388efc3f" TypeCode="0" Name="集控楼13.1米2号会议室" ParentName="集控楼13.1m层|集控楼" ParentId="0" ModelName="其他_单联单控开关_3D" KKSCode="" Abutment_DevID="0x006FA6FD325FC4924CE1B9DA6CD4EF738045" XPos="39.3799" YPos="1.77372" ZPos="10.9714" RotationX="0.000132278" RotationY="5.20686E-26" RotationZ="4.85314E-20" ScaleX="1" ScaleY="1" ScaleZ="1" DoorId="5" Local_DevId="b9b19f92-9606-469f-923d-8b62388efc3f" />
  <DoorAccessDevices DevId="2382974c-88de-4322-9944-cd8a1f0c5ffb" TypeCode="0" Name="集控楼13.1米3号运行人员办公室" ParentName="集控楼13.1m层|集控楼" ParentId="0" ModelName="其他_单联单控开关_3D" KKSCode="" Abutment_DevID="0x006F260C166E8540498684DCCC7FF906876E" XPos="42.5354" YPos="1.77372" ZPos="12.6424" RotationX="-0.000132278" RotationY="180" RotationZ="-1.15641E-11" ScaleX="1" ScaleY="1" ScaleZ="1" DoorId="6" Local_DevId="2382974c-88de-4322-9944-cd8a1f0c5ffb" />
  <DoorAccessDevices DevId="405fc3cd-7c91-41ff-8a81-ff9c3bee9432" TypeCode="0" Name="集控楼13.1米2号运行人员办公室" ParentName="集控楼13.1m层|集控楼" ParentId="0" ModelName="其他_单联单控开关_3D" KKSCode="" Abutment_DevID="0x006F613E65E4216141849BF1635AB159E325" XPos="35.8122" YPos="1.77372" ZPos="12.6424" RotationX="-0.000132278" RotationY="180" RotationZ="-1.15641E-11" ScaleX="1" ScaleY="1" ScaleZ="1" DoorId="3" Local_DevId="405fc3cd-7c91-41ff-8a81-ff9c3bee9432" />
  <DoorAccessDevices DevId="9edea8da-8e7e-492c-b4f8-6727af00fea0" TypeCode="0" Name="集控楼13.1米1号运行人员办公室" ParentName="集控楼13.1m层|集控楼" ParentId="0" ModelName="其他_单联单控开关_3D" KKSCode="" Abutment_DevID="0x006F3E44BEBE30A3490586356386E06EBD6B" XPos="29.3086" YPos="1.77372" ZPos="12.6424" RotationX="-0.000132278" RotationY="180" RotationZ="-1.15641E-11" ScaleX="1" ScaleY="1" ScaleZ="1" DoorId="1" Local_DevId="9edea8da-8e7e-492c-b4f8-6727af00fea0" />
  <DoorAccessDevices DevId="d9981a13-8131-4564-8878-02410175a965" TypeCode="0" Name="集控楼13.1米仿真室（兼巡更）" ParentName="集控楼13.1m层|集控楼" ParentId="0" ModelName="其他_单联单控开关_3D" KKSCode="" Abutment_DevID="0x006F40413C9392764B4EB202C4F425801C03" XPos="18.9872" YPos="1.77372" ZPos="10.5663" RotationX="0.000132278" RotationY="0" RotationZ="4.85314E-20" ScaleX="1" ScaleY="1" ScaleZ="1" DoorId="0" Local_DevId="d9981a13-8131-4564-8878-02410175a965" />
  <DoorAccessDevices DevId="4246948c-8bdc-4bd2-88b5-20f549a76811" TypeCode="0" Name="#1机组0米就地MCC配电间(兼巡更)" ParentName="主厂房0m层|主厂房" ParentId="0" ModelName="其他_单联单控开关_3D" KKSCode="" Abutment_DevID="0x006F6FC5262DAA8D4B02A8F4583886AE09BD" XPos="4.81437" YPos="1.5879" ZPos="109.646" RotationX="-9.33467E-06" RotationY="180" RotationZ="-8.16063E-13" ScaleX="1" ScaleY="1" ScaleZ="1" DoorId="5" Local_DevId="4246948c-8bdc-4bd2-88b5-20f549a76811" />
  <DoorAccessDevices DevId="e33b7ed1-61b1-4593-80fe-41860a0fb688" TypeCode="0" Name="#1机组0米6KV配电间(兼巡更)" ParentName="主厂房0m层|主厂房" ParentId="0" ModelName="其他_单联单控开关_3D" KKSCode="" Abutment_DevID="0x006F0777E57522E745C68B7BE2EC44482227" XPos="22.4164" YPos="1.5879" ZPos="85.1548" RotationX="-4.07111E-13" RotationY="90" RotationZ="9.33467E-06" ScaleX="1" ScaleY="1" ScaleZ="1" DoorId="6" Local_DevId="e33b7ed1-61b1-4593-80fe-41860a0fb688" />
  <DoorAccessDevices DevId="99d02209-de1c-4404-9330-e110b74216e8" TypeCode="0" Name="#2机组0米就地MCC配电间(兼巡更)" ParentName="主厂房0m层|主厂房" ParentId="0" ModelName="其他_单联单控开关_3D" KKSCode="" Abutment_DevID="0x006F5054232DB45442A4A8B4B6C5B5574BD4" XPos="5.28737" YPos="1.5879" ZPos="33.0998" RotationX="-9.33467E-06" RotationY="180" RotationZ="-8.16063E-13" ScaleX="1" ScaleY="1" ScaleZ="1" DoorId="9" Local_DevId="99d02209-de1c-4404-9330-e110b74216e8" />
  <DoorAccessDevices DevId="75c083fe-52ea-4c79-80a5-a22666619209" TypeCode="0" Name="#2机组0米6KV配电间(兼巡更)" ParentName="主厂房0m层|主厂房" ParentId="0" ModelName="其他_单联单控开关_3D" KKSCode="" Abutment_DevID="0x006FD9623621FBCC421293EF9CDA64524343" XPos="22.4164" YPos="1.5879" ZPos="8.70959" RotationX="-4.07111E-13" RotationY="90" RotationZ="9.33467E-06" ScaleX="1" ScaleY="1" ScaleZ="1" DoorId="10" Local_DevId="75c083fe-52ea-4c79-80a5-a22666619209" />
  <DoorAccessDevices DevId="ceaa0ecf-0ae5-4717-884a-50e2954f5e15" TypeCode="0" Name="#1机组4.5米燃机电子间(兼巡更)" ParentName="主厂房4.5m层|主厂房" ParentId="0" ModelName="其他_单联单控开关_3D" KKSCode="" Abutment_DevID="0x006F5449AA60062D493BBA8C7E29D5FE7692" XPos="2.53388" YPos="5.72657" ZPos="116.955" RotationX="9.33467E-06" RotationY="0" RotationZ="0" ScaleX="1" ScaleY="1" ScaleZ="1" DoorId="10" Local_DevId="ceaa0ecf-0ae5-4717-884a-50e2954f5e15" />
  <DoorAccessDevices DevId="f97abdb2-394e-4788-a1a8-1975eacdf4ad" TypeCode="0" Name="#1机组4.5米汽机励磁小室(兼巡更)" ParentName="主厂房4.5m层|主厂房" ParentId="0" ModelName="其他_单联单控开关_3D" KKSCode="" Abutment_DevID="0x006F478C2CB0C62046C6A559883EE7450A2E" XPos="13.0748" YPos="5.72657" ZPos="115.908" RotationX="-4.07111E-13" RotationY="90" RotationZ="9.33467E-06" ScaleX="1" ScaleY="1" ScaleZ="1" DoorId="9" Local_DevId="f97abdb2-394e-4788-a1a8-1975eacdf4ad" />
  <DoorAccessDevices DevId="1ff1618e-4357-4604-b50d-c74e90bf396d" TypeCode="0" Name="#1机组4.5米燃机配电间(兼巡更)" ParentName="主厂房4.5m层|主厂房" ParentId="0" ModelName="其他_单联单控开关_3D" KKSCode="" Abutment_DevID="0x006FE84F480FACF44BD6B11D63AD0F1F2030" XPos="19.6629" YPos="7.21312" ZPos="81.9816" RotationX="-4.07111E-13" RotationY="90" RotationZ="9.33467E-06" ScaleX="1" ScaleY="1" ScaleZ="1" DoorId="6" Local_DevId="1ff1618e-4357-4604-b50d-c74e90bf396d" />
  <DoorAccessDevices DevId="37fe89c9-5ea3-4921-be5d-128b691600d7" TypeCode="0" Name="#1机组4.5米燃机励磁间(兼巡更)" ParentName="主厂房4.5m层|主厂房" ParentId="0" ModelName="其他_单联单控开关_3D" KKSCode="" Abutment_DevID="0x006FC0EF0300DBF04A19846052BF1BC8B868" XPos="7.87192" YPos="7.21312" ZPos="85.9819" RotationX="9.33467E-06" RotationY="0" RotationZ="0" ScaleX="1" ScaleY="1" ScaleZ="1" DoorId="8" Local_DevId="37fe89c9-5ea3-4921-be5d-128b691600d7" />
  <DoorAccessDevices DevId="55bce9b6-5f3e-4055-ae0f-b0b114c658aa" TypeCode="0" Name="#2机组4.5米汽机励磁小室(兼巡更)" ParentName="主厂房4.5m层|主厂房" ParentId="0" ModelName="其他_单联单控开关_3D" KKSCode="" Abutment_DevID="0x006FEA2286F1FB404709AB58E328A6FD8EDD" XPos="13.0748" YPos="5.72657" ZPos="39.4126" RotationX="-4.07111E-13" RotationY="90" RotationZ="9.33467E-06" ScaleX="1" ScaleY="1" ScaleZ="1" DoorId="4" Local_DevId="55bce9b6-5f3e-4055-ae0f-b0b114c658aa" />
  <DoorAccessDevices DevId="1191add0-89d9-46cc-9d3a-77386ed733cc" TypeCode="0" Name="#2机组4.5米燃机电子间(兼巡更)" ParentName="主厂房4.5m层|主厂房" ParentId="0" ModelName="其他_单联单控开关_3D" KKSCode="" Abutment_DevID="0x006F53A106E3F29245DA9FBF04551F1FB747" XPos="2.4832" YPos="5.72657" ZPos="40.4422" RotationX="9.33467E-06" RotationY="0" RotationZ="0" ScaleX="1" ScaleY="1" ScaleZ="1" DoorId="5" Local_DevId="1191add0-89d9-46cc-9d3a-77386ed733cc" />
  <DoorAccessDevices DevId="fbb7dccf-9665-4b47-aded-8b24bcffb2c7" TypeCode="0" Name="#2机组燃机励磁室(兼巡更)" ParentName="主厂房4.5m层|主厂房" ParentId="0" ModelName="其他_单联单控开关_3D" KKSCode="" Abutment_DevID="0x006FAC69BAA059964753A3F11AC483EBEA90" XPos="7.87192" YPos="7.21312" ZPos="9.46915" RotationX="9.33467E-06" RotationY="0" RotationZ="0" ScaleX="1" ScaleY="1" ScaleZ="1" DoorId="2" Local_DevId="fbb7dccf-9665-4b47-aded-8b24bcffb2c7" />
  <DoorAccessDevices DevId="8f2eaba5-420b-4708-bce5-db486d797d03" TypeCode="0" Name="#2机组4.5米燃机配电间(兼巡更)" ParentName="主厂房4.5m层|主厂房" ParentId="0" ModelName="其他_单联单控开关_3D" KKSCode="" Abutment_DevID="0x006F1E387EA0617A4B9E88DC558B2D573FE1" XPos="19.6629" YPos="7.21312" ZPos="5.46881" RotationX="-4.07111E-13" RotationY="90" RotationZ="9.33467E-06" ScaleX="1" ScaleY="1" ScaleZ="1" DoorId="0" Local_DevId="8f2eaba5-420b-4708-bce5-db486d797d03" />
  <DoorAccessDevices DevId="1425bd72-c128-4b08-a126-111f01aa8748" TypeCode="0" Name="联合车间0米空压机房" ParentName="联合车间0m层|联合车间" ParentId="0" ModelName="其他_单联单控开关_3D" KKSCode="" Abutment_DevID="0x006FA600DDBCC3C749718F5BBA4AF7CB435D" XPos="36.5217" YPos="1.45276" ZPos="23.6813" RotationX="1.61649E-05" RotationY="0" RotationZ="0" ScaleX="1" ScaleY="1" ScaleZ="1" DoorId="0" Local_DevId="1425bd72-c128-4b08-a126-111f01aa8748" />
  <DoorAccessDevices DevId="89a87060-c96d-4e9a-a160-b4046de92414" TypeCode="0" Name="联合车间0米进气冷却装置空调机房" ParentName="联合车间0m层|联合车间" ParentId="0" ModelName="其他_单联单控开关_3D" KKSCode="" Abutment_DevID="0x006F9ABC813E16AD4A79B00A880ECE19D339" XPos="22.2475" YPos="1.63858" ZPos="23.6644" RotationX="1.61649E-05" RotationY="0" RotationZ="0" ScaleX="1" ScaleY="1" ScaleZ="1" DoorId="1" Local_DevId="89a87060-c96d-4e9a-a160-b4046de92414" />
  <DoorAccessDevices DevId="5ac1c6e2-16ee-4ea9-8be7-6880c7ab0132" TypeCode="0" Name="联合车间0米工作段配电室" ParentName="联合车间0m层|联合车间" ParentId="0" ModelName="其他_单联单控开关_3D" KKSCode="" Abutment_DevID="0x006FECFB182D4A97447FB306B63BAD7DB72A" XPos="18.4804" YPos="1.45276" ZPos="10.9376" RotationX="1.61649E-05" RotationY="0" RotationZ="0" ScaleX="1" ScaleY="1" ScaleZ="1" DoorId="9" Local_DevId="5ac1c6e2-16ee-4ea9-8be7-6880c7ab0132" />
  <DoorAccessDevices DevId="cbe46759-b642-425a-93aa-2a01cdbe058f" TypeCode="0" Name="联合车间0米电子设备间" ParentName="联合车间0m层|联合车间" ParentId="0" ModelName="其他_单联单控开关_3D" KKSCode="" Abutment_DevID="0x006FADB34922A3F441DBA65A3B312887A27A" XPos="16.2675" YPos="1.45276" ZPos="12.2373" RotationX="0" RotationY="90" RotationZ="1.61649E-05" ScaleX="1" ScaleY="1" ScaleZ="1" DoorId="10" Local_DevId="cbe46759-b642-425a-93aa-2a01cdbe058f" />
  <DoorAccessDevices DevId="7b2f30b0-49be-480d-bbed-84f2a398290e" TypeCode="0" Name="联合车间4.5米进气冷却装置配电间" ParentName="联合车间4.5m层|联合车间" ParentId="0" ModelName="其他_单联单控开关_3D" KKSCode="" Abutment_DevID="0x006F7E59117D0A794ACE91DC9FE6815BAB2B" XPos="25.5955" YPos="1.49981" ZPos="12.136" RotationX="1.62844E-12" RotationY="270" RotationZ="-3.66554E-05" ScaleX="1" ScaleY="1" ScaleZ="1" DoorId="0" Local_DevId="7b2f30b0-49be-480d-bbed-84f2a398290e" />
  <DoorAccessDevices DevId="fda3be13-3215-4375-b014-c6f983c089f4" TypeCode="0" Name="联合车间4.5米1号电缆夹层" ParentName="联合车间4.5m层|联合车间" ParentId="0" ModelName="其他_单联单控开关_3D" KKSCode="" Abutment_DevID="0x006F5A7D00DDEBF14B42A59FB069D2FB893F" XPos="22.4366" YPos="1.49981" ZPos="15.8494" RotationX="-3.25689E-12" RotationY="90" RotationZ="3.66554E-05" ScaleX="1" ScaleY="1" ScaleZ="1" DoorId="1" Local_DevId="fda3be13-3215-4375-b014-c6f983c089f4" />
  <DoorAccessDevices DevId="966d264a-a876-41a7-985a-35f3a23eafae" TypeCode="0" Name="联合车间4.5米2号电缆夹层" ParentName="联合车间4.5m层|联合车间" ParentId="0" ModelName="其他_单联单控开关_3D" KKSCode="" Abutment_DevID="0x006F13F770E2313B457CB19DF10EC3852CC5" XPos="23.8387" YPos="1.21264" ZPos="8.89526" RotationX="-3.25689E-12" RotationY="90" RotationZ="3.66554E-05" ScaleX="1" ScaleY="1" ScaleZ="1" DoorId="2" Local_DevId="966d264a-a876-41a7-985a-35f3a23eafae" />
  <DoorAccessDevices DevId="ea2634c9-726d-4996-b175-1e8e879c5fcc" TypeCode="0" Name="联合车间4.5米消防气瓶间" ParentName="联合车间4.5m层|联合车间" ParentId="0" ModelName="其他_单联单控开关_3D" KKSCode="" Abutment_DevID="0x006F581F4F81AAF44037B1129DA8F87FE491" XPos="4.61492" YPos="1.49981" ZPos="14.229" RotationX="-3.25689E-12" RotationY="90" RotationZ="3.66554E-05" ScaleX="1" ScaleY="1" ScaleZ="1" DoorId="6" Local_DevId="ea2634c9-726d-4996-b175-1e8e879c5fcc" />
  <DoorAccessDevices DevId="65d1c5d3-1951-4645-8184-34045868d61d" TypeCode="0" Name="联合车间7.8米公用段配电间" ParentName="联合车间7.8m层|联合车间" ParentId="0" ModelName="其他_单联单控开关_3D" KKSCode="" Abutment_DevID="0x006F5128AD9719F74ABF8466AC5B990C741C" XPos="23.4637" YPos="2.68038" ZPos="10.9207" RotationX="1.61649E-05" RotationY="2.89272E-27" RotationZ="4.85314E-20" ScaleX="1" ScaleY="1" ScaleZ="1" DoorId="6" Local_DevId="65d1c5d3-1951-4645-8184-34045868d61d" />
  <DoorAccessDevices DevId="0288eab6-aa80-4306-8c06-c4b728d67770" TypeCode="0" Name="联合车间7.8米继电器室" ParentName="联合车间7.8m层|联合车间" ParentId="0" ModelName="其他_单联单控开关_3D" KKSCode="" Abutment_DevID="0x006FB246CF19BEFF4B49888A2A2D80DB11CE" XPos="19.2744" YPos="2.68038" ZPos="12.5411" RotationX="-1.61649E-05" RotationY="180" RotationZ="-1.41318E-12" ScaleX="1" ScaleY="1" ScaleZ="1" DoorId="1" Local_DevId="0288eab6-aa80-4306-8c06-c4b728d67770" />
  <DoorAccessDevices DevId="315ce4bd-88c3-47f2-842e-70c3fb2f2948" TypeCode="0" Name="联合车间7.8米蓄电池室" ParentName="联合车间7.8m层|联合车间" ParentId="0" ModelName="其他_单联单控开关_3D" KKSCode="" Abutment_DevID="0x006F4D43D900F943441589C3EFA43E318175" XPos="4.67923" YPos="2.68038" ZPos="13.8915" RotationX="8.14222E-13" RotationY="90" RotationZ="1.61649E-05" ScaleX="1" ScaleY="1" ScaleZ="1" DoorId="4" Local_DevId="315ce4bd-88c3-47f2-842e-70c3fb2f2948" />
  <DoorAccessDevices DevId="53a6a8cb-9718-403c-a8cb-18265f8e748d" TypeCode="0" Name="废水站电子设备间" ParentName="废水集中处理站0m层|废水集中处理站" ParentId="0" ModelName="其他_单联单控开关_3D" KKSCode="" Abutment_DevID="0x006F283A031733794B1598C624A221A98B76" XPos="9.49361" YPos="1.5879" ZPos="41.5056" RotationX="0" RotationY="90" RotationZ="2.2995E-05" ScaleX="1" ScaleY="1" ScaleZ="1" DoorId="4" Local_DevId="53a6a8cb-9718-403c-a8cb-18265f8e748d" />
  <DoorAccessDevices DevId="2e8e9c12-7a59-4ea0-ba29-3f0272211cd4" TypeCode="0" Name="废水站配电间" ParentName="废水集中处理站0m层|废水集中处理站" ParentId="0" ModelName="其他_单联单控开关_3D" KKSCode="" Abutment_DevID="0x006FCFAD06C4864242FEA15303E398A73238" XPos="9.49361" YPos="1.5879" ZPos="34.9228" RotationX="0" RotationY="90" RotationZ="2.2995E-05" ScaleX="1" ScaleY="1" ScaleZ="1" DoorId="3" Local_DevId="2e8e9c12-7a59-4ea0-ba29-3f0272211cd4" />
  <DoorAccessDevices DevId="7037094d-2b36-4f55-b6bb-82b64c8f94cb" TypeCode="0" Name="废水站药品贮藏间" ParentName="废水集中处理站0m层|废水集中处理站" ParentId="0" ModelName="其他_单联单控开关_3D" KKSCode="" Abutment_DevID="0x006FBD7461678736400AB44D52B78E6823AB" XPos="9.49361" YPos="1.5879" ZPos="28.9138" RotationX="0" RotationY="90" RotationZ="2.2995E-05" ScaleX="1" ScaleY="1" ScaleZ="1" DoorId="2" Local_DevId="7037094d-2b36-4f55-b6bb-82b64c8f94cb" />
  <DoorAccessDevices DevId="a16ae782-c936-43d4-9ba0-f8cfba170c2e" TypeCode="0" Name="废水站加药间" ParentName="废水集中处理站0m层|废水集中处理站" ParentId="0" ModelName="其他_单联单控开关_3D" KKSCode="" Abutment_DevID="0x006FEA2BC987D187443E958A1E11710CC530" XPos="9.49361" YPos="1.5879" ZPos="26.1119" RotationX="0" RotationY="90" RotationZ="2.2995E-05" ScaleX="1" ScaleY="1" ScaleZ="1" DoorId="1" Local_DevId="a16ae782-c936-43d4-9ba0-f8cfba170c2e" />
  <DoorAccessDevices DevId="948f7191-8ddc-4854-b8f8-e474e802d88d" TypeCode="0" Name="酸碱储存室15-1" ParentName="废水集中处理站0m层|废水集中处理站" ParentId="0" ModelName="其他_单联单控开关_3D" KKSCode="" Abutment_DevID="0x006F6C924371DB7446D0837154D40ACB3CC1" XPos="9.49361" YPos="1.5879" ZPos="8.20322" RotationX="0" RotationY="90" RotationZ="2.2995E-05" ScaleX="1" ScaleY="1" ScaleZ="1" DoorId="0" Local_DevId="948f7191-8ddc-4854-b8f8-e474e802d88d" />
  <DoorAccessDevices DevId="af0444c4-e954-4776-afbe-8eb076ee8fbc" TypeCode="0" Name="锅炉补给水0米层1号楼梯" ParentName="锅炉补给水处理车间0m层|锅炉补给水处理车间" ParentId="0" ModelName="其他_单联单控开关_3D" KKSCode="" Abutment_DevID="0x006F7A3D3755EF5944548EE288E5243CA9D2" XPos="32.4844" YPos="1.73993" ZPos="3.79779" RotationX="0" RotationY="90" RotationZ="2.50448E-06" ScaleX="1" ScaleY="1" ScaleZ="1" DoorId="3" Local_DevId="af0444c4-e954-4776-afbe-8eb076ee8fbc" />
  <DoorAccessDevices DevId="d70d92ba-96e4-402d-9b90-5ee5b5a0047a" TypeCode="0" Name="锅炉补给水0米2号楼梯" ParentName="锅炉补给水处理车间0m层|锅炉补给水处理车间" ParentId="0" ModelName="其他_单联单控开关_3D" KKSCode="" Abutment_DevID="0x006FC336B53E537C4AD8B52F4B73EA4F20B7" XPos="32.4844" YPos="1.73993" ZPos="33.2517" RotationX="0" RotationY="90" RotationZ="2.50448E-06" ScaleX="1" ScaleY="1" ScaleZ="1" DoorId="1" Local_DevId="d70d92ba-96e4-402d-9b90-5ee5b5a0047a" />
  <DoorAccessDevices DevId="44bf591f-44fe-417e-ad36-236af70f660d" TypeCode="0" Name="锅炉补给水0米除盐间2号门" ParentName="锅炉补给水处理车间0m层|锅炉补给水处理车间" ParentId="0" ModelName="其他_单联单控开关_3D" KKSCode="" Abutment_DevID="0x006F379C14292DE44E9EA1B4B20097812BC4" XPos="8.53073" YPos="1.73993" ZPos="61.8786" RotationX="2.50448E-06" RotationY="0" RotationZ="0" ScaleX="1" ScaleY="1" ScaleZ="1" DoorId="8" Local_DevId="44bf591f-44fe-417e-ad36-236af70f660d" />
  <DoorAccessDevices DevId="e6b55a38-cd7f-4229-ac29-5badd0c37fae" TypeCode="0" Name="锅炉补给水0米层加压间" ParentName="锅炉补给水处理车间0m层|锅炉补给水处理车间" ParentId="0" ModelName="其他_单联单控开关_3D" KKSCode="" Abutment_DevID="0x006FAAAA8E40A45349C8B872FC8BA7327178" XPos="21.5549" YPos="1.68925" ZPos="38.3661" RotationX="0" RotationY="270" RotationZ="-2.50448E-06" ScaleX="1" ScaleY="1" ScaleZ="1" DoorId="11" Local_DevId="e6b55a38-cd7f-4229-ac29-5badd0c37fae" />
  <DoorAccessDevices DevId="43c47405-4c32-4628-8fa4-905c977eaf8a" TypeCode="0" Name="锅炉补给水0米电子设备间" ParentName="锅炉补给水处理车间0m层|锅炉补给水处理车间" ParentId="0" ModelName="其他_单联单控开关_3D" KKSCode="" Abutment_DevID="0x006FD7013C89399D4366926021015942950F" XPos="21.5549" YPos="1.68925" ZPos="26.9052" RotationX="0" RotationY="270" RotationZ="-2.50448E-06" ScaleX="1" ScaleY="1" ScaleZ="1" DoorId="12" Local_DevId="43c47405-4c32-4628-8fa4-905c977eaf8a" />
  <DoorAccessDevices DevId="203ea7a3-27c7-46e9-8f50-568791a4898f" TypeCode="0" Name="锅炉补给水0米层配电间" ParentName="锅炉补给水处理车间0m层|锅炉补给水处理车间" ParentId="0" ModelName="其他_单联单控开关_3D" KKSCode="" Abutment_DevID="0x006F777C61CE73434A879FF4E4BAD4BA47C9" XPos="21.5549" YPos="1.68925" ZPos="7.91628" RotationX="0" RotationY="270" RotationZ="-2.50448E-06" ScaleX="1" ScaleY="1" ScaleZ="1" DoorId="18" Local_DevId="203ea7a3-27c7-46e9-8f50-568791a4898f" />
  <DoorAccessDevices DevId="b10db414-3a51-4a38-ae29-947587319dcd" TypeCode="0" Name="锅炉补给水0米除盐间1号门" ParentName="锅炉补给水处理车间0m层|锅炉补给水处理车间" ParentId="0" ModelName="其他_单联单控开关_3D" KKSCode="" Abutment_DevID="0x006FD516DCE0196044B883032DCF91CC2F4B" XPos="20.8454" YPos="1.73993" ZPos="-0.337581" RotationX="-2.50448E-06" RotationY="180" RotationZ="-2.18948E-13" ScaleX="1" ScaleY="1" ScaleZ="1" DoorId="4" Local_DevId="b10db414-3a51-4a38-ae29-947587319dcd" />
  <DoorAccessDevices DevId="9fd8d7b4-068f-4745-9df0-98b0e3e7c5d1" TypeCode="0" Name="锅炉补给水0米水泵间2号门" ParentName="锅炉补给水处理车间0m层|锅炉补给水处理车间" ParentId="0" ModelName="其他_单联单控开关_3D" KKSCode="" Abutment_DevID="0x006FECCDB2099F434BC6AE536A8ABC4D3917" XPos="0.0675702" YPos="1.73993" ZPos="58.9585" RotationX="0" RotationY="270" RotationZ="-2.50448E-06" ScaleX="1" ScaleY="1" ScaleZ="1" DoorId="7" Local_DevId="9fd8d7b4-068f-4745-9df0-98b0e3e7c5d1" />
  <DoorAccessDevices DevId="c0e7c82e-a595-4af7-9411-7dc85c44610f" TypeCode="0" Name="锅炉补给水0米层水泵间1号门" ParentName="锅炉补给水处理车间0m层|锅炉补给水处理车间" ParentId="0" ModelName="其他_单联单控开关_3D" KKSCode="" Abutment_DevID="0x006FF1F18CA21882460AA3D7E5D41E15D196" XPos="0.0675702" YPos="1.73993" ZPos="31.1756" RotationX="0" RotationY="270" RotationZ="-2.50448E-06" ScaleX="1" ScaleY="1" ScaleZ="1" DoorId="6" Local_DevId="c0e7c82e-a595-4af7-9411-7dc85c44610f" />
  <DoorAccessDevices DevId="fa3c0c98-b262-45a7-8886-f8459e4deaf0" TypeCode="0" Name="净水站消防水泵房" ParentName="净水站0m层|净水站" ParentId="0" ModelName="其他_单联单控开关_3D" KKSCode="" Abutment_DevID="0x006FDC10A4F741B14DF0B295E20BE7DBC643" XPos="0.0506776" YPos="1.60479" ZPos="0.607646" RotationX="0" RotationY="270" RotationZ="-2.50448E-06" ScaleX="1" ScaleY="1" ScaleZ="1" DoorId="7" Local_DevId="fa3c0c98-b262-45a7-8886-f8459e4deaf0" />
  <DoorAccessDevices DevId="d007cf8d-d13b-4a3b-9e74-3284ebdfc179" TypeCode="0" Name="净水站油箱间" ParentName="净水站0m层|净水站" ParentId="0" ModelName="其他_单联单控开关_3D" KKSCode="" Abutment_DevID="0x006F1ADDD32657514D909B5CC3BE5C3BBBD7" XPos="4.96641" YPos="1.60479" ZPos="13.7733" RotationX="0" RotationY="270" RotationZ="-2.50448E-06" ScaleX="1" ScaleY="1" ScaleZ="1" DoorId="9" Local_DevId="d007cf8d-d13b-4a3b-9e74-3284ebdfc179" />
  <DoorAccessDevices DevId="4b8df1b7-6709-46d2-9204-c5ec0186d8f2" TypeCode="0" Name="净水站加药间" ParentName="净水站0m层|净水站" ParentId="0" ModelName="其他_单联单控开关_3D" KKSCode="" Abutment_DevID="0x006FB02CF0DF6AA840B28296A6E50366826F" XPos="0.0506776" YPos="1.60479" ZPos="44.7801" RotationX="0" RotationY="270" RotationZ="-2.50448E-06" ScaleX="1" ScaleY="1" ScaleZ="1" DoorId="1" Local_DevId="4b8df1b7-6709-46d2-9204-c5ec0186d8f2" />
  <DoorAccessDevices DevId="77d1b2ec-4097-426d-b7b0-e7d83f07417f" TypeCode="0" Name="净水站加氯间" ParentName="净水站0m层|净水站" ParentId="0" ModelName="其他_单联单控开关_3D" KKSCode="" Abutment_DevID="0x006FF8C451BD90B147959D653A9A9F49550B" XPos="0.0506776" YPos="1.60479" ZPos="50.7891" RotationX="0" RotationY="270" RotationZ="-2.50448E-06" ScaleX="1" ScaleY="1" ScaleZ="1" DoorId="0" Local_DevId="77d1b2ec-4097-426d-b7b0-e7d83f07417f" />
</DoorAccessList>