<?xml version="1.0" encoding="utf-8"?>
<DevMonitorNodeList xmlns:xsi="http://www.w3.org/2001/XMLSchema-instance" xmlns:xsd="http://www.w3.org/2001/XMLSchema">
  <DevMonitorNode Id="33301" TagName="40PGA00AA031CD" Describe="水水交换器A闭式循环水入口阀关" Unit="" ParentKKS="4号机组闭式冷却水泵" Time="0" />
  <DevMonitorNode Id="4133" TagName="40PGA00AA031CP" Describe="水水交换器A闭式循环水入口阀关" Unit="" ParentKKS="4号机组闭式冷却水泵" Time="0" />
  <DevMonitorNode Id="33303" TagName="40PGA00AA031RL" Describe="水水交换器A闭式循环水入口阀在" Unit="" ParentKKS="4号机组闭式冷却水泵" Time="0" />
  <DevMonitorNode Id="4135" TagName="40PGA00AA031OP" Describe="水水交换器A闭式循环水入口阀打" Unit="" ParentKKS="4号机组闭式冷却水泵" Time="0" />
  <DevMonitorNode Id="33302" TagName="40PGA00AA031OD" Describe="水水交换器A闭式循环水入口阀打" Unit="" ParentKKS="4号机组闭式冷却水泵" Time="0" />
  <DevMonitorNode Id="4134" TagName="40PGA00AA031F" Describe="水水交换器A闭式循环水入口阀故" Unit="" ParentKKS="4号机组闭式冷却水泵" Time="0" />
  <DevMonitorNode Id="33307" TagName="40PGA00AA041CD" Describe="水水交换器A闭式循环水出口阀关" Unit="" ParentKKS="4号机组闭式冷却水泵" Time="0" />
  <DevMonitorNode Id="4136" TagName="40PGA00AA041CP" Describe="水水交换器A闭式循环水出口阀关" Unit="" ParentKKS="4号机组闭式冷却水泵" Time="0" />
  <DevMonitorNode Id="33309" TagName="40PGA00AA041RL" Describe="水水交换器A闭式循环水出口阀在" Unit="" ParentKKS="4号机组闭式冷却水泵" Time="0" />
  <DevMonitorNode Id="33308" TagName="40PGA00AA041OD" Describe="水水交换器A闭式循环水出口阀打" Unit="" ParentKKS="4号机组闭式冷却水泵" Time="0" />
  <DevMonitorNode Id="4138" TagName="40PGA00AA041OP" Describe="水水交换器A闭式循环水出口阀打" Unit="" ParentKKS="4号机组闭式冷却水泵" Time="0" />
  <DevMonitorNode Id="4137" TagName="40PGA00AA041F" Describe="水水交换器A闭式循环水出口阀故" Unit="" ParentKKS="4号机组闭式冷却水泵" Time="0" />
  <DevMonitorNode Id="33304" TagName="40PGA00AA032CD" Describe="水水交换器B闭式循环水入口阀关" Unit="" ParentKKS="4号机组闭式冷却水泵" Time="0" />
  <DevMonitorNode Id="3953" TagName="40PGA00AA032CP" Describe="水水交换器B闭式循环水入口阀关" Unit="" ParentKKS="4号机组闭式冷却水泵" Time="0" />
  <DevMonitorNode Id="33306" TagName="40PGA00AA032RL" Describe="水水交换器B闭式循环水入口阀在" Unit="" ParentKKS="4号机组闭式冷却水泵" Time="0" />
  <DevMonitorNode Id="33305" TagName="40PGA00AA032OD" Describe="水水交换器B闭式循环水入口阀打" Unit="" ParentKKS="4号机组闭式冷却水泵" Time="0" />
  <DevMonitorNode Id="3955" TagName="40PGA00AA032OP" Describe="水水交换器B闭式循环水入口阀打" Unit="" ParentKKS="4号机组闭式冷却水泵" Time="0" />
  <DevMonitorNode Id="3954" TagName="40PGA00AA032F" Describe="水水交换器B闭式循环水入口阀故" Unit="" ParentKKS="4号机组闭式冷却水泵" Time="0" />
  <DevMonitorNode Id="33310" TagName="40PGA00AA042CD" Describe="水水交换器B闭式循环水出口阀关" Unit="" ParentKKS="4号机组闭式冷却水泵" Time="0" />
  <DevMonitorNode Id="3956" TagName="40PGA00AA042CP" Describe="水水交换器B闭式循环水出口阀关" Unit="" ParentKKS="4号机组闭式冷却水泵" Time="0" />
  <DevMonitorNode Id="33312" TagName="40PGA00AA042RL" Describe="水水交换器B闭式循环水出口阀在" Unit="" ParentKKS="4号机组闭式冷却水泵" Time="0" />
  <DevMonitorNode Id="3958" TagName="40PGA00AA042OP" Describe="水水交换器B闭式循环水出口阀打" Unit="" ParentKKS="4号机组闭式冷却水泵" Time="0" />
  <DevMonitorNode Id="33311" TagName="40PGA00AA042OD" Describe="水水交换器B闭式循环水出口阀打" Unit="" ParentKKS="4号机组闭式冷却水泵" Time="0" />
  <DevMonitorNode Id="3957" TagName="40PGA00AA042F" Describe="水水交换器B闭式循环水出口阀故" Unit="" ParentKKS="4号机组闭式冷却水泵" Time="0" />
  <DevMonitorNode Id="53921" TagName="40PGA00AA022-HWFA" Describe="硬件故障" Unit="" ParentKKS="4号机组闭式冷却水泵" Time="0" />
  <DevMonitorNode Id="53976" TagName="40PGA00AP001-HWFA" Describe="硬件故障" Unit="" ParentKKS="4号机组闭式冷却水泵" Time="0" />
  <DevMonitorNode Id="53990" TagName="40PGA00AP002-HWFA" Describe="硬件故障" Unit="" ParentKKS="4号机组闭式冷却水泵" Time="0" />
  <DevMonitorNode Id="53943" TagName="40PGA00AA032-HWFA" Describe="硬件故障" Unit="" ParentKKS="4号机组闭式冷却水泵" Time="0" />
  <DevMonitorNode Id="53932" TagName="40PGA00AA031-HWFA" Describe="硬件故障" Unit="" ParentKKS="4号机组闭式冷却水泵" Time="0" />
  <DevMonitorNode Id="53954" TagName="40PGA00AA041-HWFA" Describe="硬件故障" Unit="" ParentKKS="4号机组闭式冷却水泵" Time="0" />
  <DevMonitorNode Id="53910" TagName="40PGA00AA021-HWFA" Describe="硬件故障" Unit="" ParentKKS="4号机组闭式冷却水泵" Time="0" />
  <DevMonitorNode Id="53965" TagName="40PGA00AA042-HWFA" Describe="硬件故障" Unit="" ParentKKS="4号机组闭式冷却水泵" Time="0" />
  <DevMonitorNode Id="53927" TagName="40PGA00AA031-AUT" Describe="置自动" Unit="" ParentKKS="4号机组闭式冷却水泵" Time="0" />
  <DevMonitorNode Id="53971" TagName="40PGA00AP001-AUT" Describe="置自动" Unit="" ParentKKS="4号机组闭式冷却水泵" Time="0" />
  <DevMonitorNode Id="53949" TagName="40PGA00AA041-AUT" Describe="置自动" Unit="" ParentKKS="4号机组闭式冷却水泵" Time="0" />
  <DevMonitorNode Id="53905" TagName="40PGA00AA021-AUT" Describe="置自动" Unit="" ParentKKS="4号机组闭式冷却水泵" Time="0" />
  <DevMonitorNode Id="53960" TagName="40PGA00AA042-AUT" Describe="置自动" Unit="" ParentKKS="4号机组闭式冷却水泵" Time="0" />
  <DevMonitorNode Id="53938" TagName="40PGA00AA032-AUT" Describe="置自动" Unit="" ParentKKS="4号机组闭式冷却水泵" Time="0" />
  <DevMonitorNode Id="53916" TagName="40PGA00AA022-AUT" Describe="置自动" Unit="" ParentKKS="4号机组闭式冷却水泵" Time="0" />
  <DevMonitorNode Id="53914" TagName="40PGA00AA022-ACL" Describe="自动关" Unit="" ParentKKS="4号机组闭式冷却水泵" Time="0" />
  <DevMonitorNode Id="53936" TagName="40PGA00AA032-ACL" Describe="自动关" Unit="" ParentKKS="4号机组闭式冷却水泵" Time="0" />
  <DevMonitorNode Id="53958" TagName="40PGA00AA042-ACL" Describe="自动关" Unit="" ParentKKS="4号机组闭式冷却水泵" Time="0" />
  <DevMonitorNode Id="53903" TagName="40PGA00AA021-ACL" Describe="自动关" Unit="" ParentKKS="4号机组闭式冷却水泵" Time="0" />
  <DevMonitorNode Id="53947" TagName="40PGA00AA041-ACL" Describe="自动关" Unit="" ParentKKS="4号机组闭式冷却水泵" Time="0" />
  <DevMonitorNode Id="53969" TagName="40PGA00AP001-ACL" Describe="自动关" Unit="" ParentKKS="4号机组闭式冷却水泵" Time="0" />
  <DevMonitorNode Id="53983" TagName="40PGA00AP002-ACL" Describe="自动关" Unit="" ParentKKS="4号机组闭式冷却水泵" Time="0" />
  <DevMonitorNode Id="53925" TagName="40PGA00AA031-ACL" Describe="自动关" Unit="" ParentKKS="4号机组闭式冷却水泵" Time="0" />
  <DevMonitorNode Id="53948" TagName="40PGA00AA041-AOP" Describe="自动开" Unit="" ParentKKS="4号机组闭式冷却水泵" Time="0" />
  <DevMonitorNode Id="53915" TagName="40PGA00AA022-AOP" Describe="自动开" Unit="" ParentKKS="4号机组闭式冷却水泵" Time="0" />
  <DevMonitorNode Id="53937" TagName="40PGA00AA032-AOP" Describe="自动开" Unit="" ParentKKS="4号机组闭式冷却水泵" Time="0" />
  <DevMonitorNode Id="53970" TagName="40PGA00AP001-AOP" Describe="自动开" Unit="" ParentKKS="4号机组闭式冷却水泵" Time="0" />
  <DevMonitorNode Id="53984" TagName="40PGA00AP002-AOP" Describe="自动开" Unit="" ParentKKS="4号机组闭式冷却水泵" Time="0" />
  <DevMonitorNode Id="53959" TagName="40PGA00AA042-AOP" Describe="自动开" Unit="" ParentKKS="4号机组闭式冷却水泵" Time="0" />
  <DevMonitorNode Id="53926" TagName="40PGA00AA031-AOP" Describe="自动开" Unit="" ParentKKS="4号机组闭式冷却水泵" Time="0" />
  <DevMonitorNode Id="53904" TagName="40PGA00AA021-AOP" Describe="自动开" Unit="" ParentKKS="4号机组闭式冷却水泵" Time="0" />
  <DevMonitorNode Id="53994" TagName="40PGA00AP002-SPO" Describe="超迟关" Unit="" ParentKKS="4号机组闭式冷却水泵" Time="0" />
  <DevMonitorNode Id="53981" TagName="40PGA00AP001-SPO" Describe="超迟关" Unit="" ParentKKS="4号机组闭式冷却水泵" Time="0" />
  <DevMonitorNode Id="53982" TagName="40PGA00AP001-STO" Describe="超迟开" Unit="" ParentKKS="4号机组闭式冷却水泵" Time="0" />
  <DevMonitorNode Id="53995" TagName="40PGA00AP002-STO" Describe="超迟开" Unit="" ParentKKS="4号机组闭式冷却水泵" Time="0" />
  <DevMonitorNode Id="33327" TagName="40PGA00AP001-TRIP" Describe="运行中跳闸" Unit="" ParentKKS="4号机组闭式冷却水泵" Time="0" />
  <DevMonitorNode Id="33328" TagName="40PGA00AP002-TRIP" Describe="运行中跳闸" Unit="" ParentKKS="4号机组闭式冷却水泵" Time="0" />
  <DevMonitorNode Id="3422" TagName="40PGA00CT013" Describe="闭冷水泵A定子绕组A相温度1" Unit="" ParentKKS="4号机组闭式冷却水泵" Time="0" />
  <DevMonitorNode Id="3423" TagName="40PGA00CT014" Describe="闭冷水泵A定子绕组A相温度2" Unit="" ParentKKS="4号机组闭式冷却水泵" Time="0" />
  <DevMonitorNode Id="3424" TagName="40PGA00CT015" Describe="闭冷水泵A定子绕组B相温度1" Unit="" ParentKKS="4号机组闭式冷却水泵" Time="0" />
  <DevMonitorNode Id="3425" TagName="40PGA00CT016" Describe="闭冷水泵A定子绕组B相温度2" Unit="" ParentKKS="4号机组闭式冷却水泵" Time="0" />
  <DevMonitorNode Id="3426" TagName="40PGA00CT017" Describe="闭冷水泵A定子绕组C相温度1" Unit="" ParentKKS="4号机组闭式冷却水泵" Time="0" />
  <DevMonitorNode Id="3427" TagName="40PGA00CT018" Describe="闭冷水泵A定子绕组C相温度2" Unit="" ParentKKS="4号机组闭式冷却水泵" Time="0" />
  <DevMonitorNode Id="3434" TagName="40PGA00TE011" Describe="闭冷水泵A电机前轴承温度" Unit="" ParentKKS="4号机组闭式冷却水泵" Time="0" />
  <DevMonitorNode Id="3435" TagName="40PGA00TE012" Describe="闭冷水泵A电机后轴承温度" Unit="" ParentKKS="4号机组闭式冷却水泵" Time="0" />
  <DevMonitorNode Id="3428" TagName="40PGA00CT023" Describe="闭冷水泵B定子绕组A相温度1" Unit="" ParentKKS="4号机组闭式冷却水泵" Time="0" />
  <DevMonitorNode Id="3429" TagName="40PGA00CT024" Describe="闭冷水泵B定子绕组A相温度2" Unit="" ParentKKS="4号机组闭式冷却水泵" Time="0" />
  <DevMonitorNode Id="3430" TagName="40PGA00CT025" Describe="闭冷水泵B定子绕组B相温度1" Unit="" ParentKKS="4号机组闭式冷却水泵" Time="0" />
  <DevMonitorNode Id="3431" TagName="40PGA00CT026" Describe="闭冷水泵B定子绕组B相温度2" Unit="" ParentKKS="4号机组闭式冷却水泵" Time="0" />
  <DevMonitorNode Id="3432" TagName="40PGA00CT027" Describe="闭冷水泵B定子绕组C相温度1" Unit="" ParentKKS="4号机组闭式冷却水泵" Time="0" />
  <DevMonitorNode Id="3433" TagName="40PGA00CT028" Describe="闭冷水泵B定子绕组C相温度2" Unit="" ParentKKS="4号机组闭式冷却水泵" Time="0" />
  <DevMonitorNode Id="3436" TagName="40PGA00TE021" Describe="闭冷水泵B电机前轴承温度" Unit="" ParentKKS="4号机组闭式冷却水泵" Time="0" />
  <DevMonitorNode Id="3437" TagName="40PGA00TE022" Describe="闭冷水泵B电机后轴承温度" Unit="" ParentKKS="4号机组闭式冷却水泵" Time="0" />
  <DevMonitorNode Id="52732" TagName="40PGA00AP001PS" Describe="闭式冷却水泵A保护动作" Unit="" ParentKKS="4号机组闭式冷却水泵" Time="0" />
  <DevMonitorNode Id="52731" TagName="40PGA00AP001PF" Describe="闭式冷却水泵A保护装置故障" Unit="" ParentKKS="4号机组闭式冷却水泵" Time="0" />
  <DevMonitorNode Id="4719" TagName="40PGA00AP001TP" Describe="闭式冷却水泵A停止位置" Unit="" ParentKKS="4号机组闭式冷却水泵" Time="0" />
  <DevMonitorNode Id="52736" TagName="40PGA00AP001TD" Describe="闭式冷却水泵A停止指令" Unit="" ParentKKS="4号机组闭式冷却水泵" Time="0" />
  <DevMonitorNode Id="4148" TagName="40PGA00AA021CP" Describe="闭式冷却水泵A出口阀关闭位置" Unit="" ParentKKS="4号机组闭式冷却水泵" Time="0" />
  <DevMonitorNode Id="52722" TagName="40PGA00AA021CD" Describe="闭式冷却水泵A出口阀关闭指令" Unit="" ParentKKS="4号机组闭式冷却水泵" Time="0" />
  <DevMonitorNode Id="52725" TagName="40PGA00AA021RL" Describe="闭式冷却水泵A出口阀在遥控位" Unit="" ParentKKS="4号机组闭式冷却水泵" Time="0" />
  <DevMonitorNode Id="4150" TagName="40PGA00AA021OP" Describe="闭式冷却水泵A出口阀打开位置" Unit="" ParentKKS="4号机组闭式冷却水泵" Time="0" />
  <DevMonitorNode Id="52724" TagName="40PGA00AA021OD" Describe="闭式冷却水泵A出口阀打开指令" Unit="" ParentKKS="4号机组闭式冷却水泵" Time="0" />
  <DevMonitorNode Id="52723" TagName="40PGA00AA021F" Describe="闭式冷却水泵A出口阀故障" Unit="" ParentKKS="4号机组闭式冷却水泵" Time="0" />
  <DevMonitorNode Id="4153" TagName="40PGA00AP001RP" Describe="闭式冷却水泵A启动位置" Unit="" ParentKKS="4号机组闭式冷却水泵" Time="0" />
  <DevMonitorNode Id="52734" TagName="40PGA00AP001RD" Describe="闭式冷却水泵A启动指令" Unit="" ParentKKS="4号机组闭式冷却水泵" Time="0" />
  <DevMonitorNode Id="52735" TagName="40PGA00AP001SE" Describe="闭式冷却水泵A弹簧已储能" Unit="" ParentKKS="4号机组闭式冷却水泵" Time="0" />
  <DevMonitorNode Id="52730" TagName="40PGA00AP001LP" Describe="闭式冷却水泵A控制回路断线" Unit="" ParentKKS="4号机组闭式冷却水泵" Time="0" />
  <DevMonitorNode Id="52733" TagName="40PGA00AP001RC" Describe="闭式冷却水泵A远方位置" Unit="" ParentKKS="4号机组闭式冷却水泵" Time="0" />
  <DevMonitorNode Id="52739" TagName="40PGA00AP002PS" Describe="闭式冷却水泵B保护动作" Unit="" ParentKKS="4号机组闭式冷却水泵" Time="0" />
  <DevMonitorNode Id="52738" TagName="40PGA00AP002PF" Describe="闭式冷却水泵B保护装置故障" Unit="" ParentKKS="4号机组闭式冷却水泵" Time="0" />
  <DevMonitorNode Id="4720" TagName="40PGA00AP002TP" Describe="闭式冷却水泵B停止位置" Unit="" ParentKKS="4号机组闭式冷却水泵" Time="0" />
  <DevMonitorNode Id="52743" TagName="40PGA00AP002TD" Describe="闭式冷却水泵B停止指令" Unit="" ParentKKS="4号机组闭式冷却水泵" Time="0" />
  <DevMonitorNode Id="3930" TagName="40PGA00AA022CP" Describe="闭式冷却水泵B出口阀关闭位置" Unit="" ParentKKS="4号机组闭式冷却水泵" Time="0" />
  <DevMonitorNode Id="52726" TagName="40PGA00AA022CD" Describe="闭式冷却水泵B出口阀关闭指令" Unit="" ParentKKS="4号机组闭式冷却水泵" Time="0" />
  <DevMonitorNode Id="52729" TagName="40PGA00AA022RL" Describe="闭式冷却水泵B出口阀在遥控位" Unit="" ParentKKS="4号机组闭式冷却水泵" Time="0" />
  <DevMonitorNode Id="3932" TagName="40PGA00AA022OP" Describe="闭式冷却水泵B出口阀打开位置" Unit="" ParentKKS="4号机组闭式冷却水泵" Time="0" />
  <DevMonitorNode Id="52728" TagName="40PGA00AA022OD" Describe="闭式冷却水泵B出口阀打开指令" Unit="" ParentKKS="4号机组闭式冷却水泵" Time="0" />
  <DevMonitorNode Id="52727" TagName="40PGA00AA022F" Describe="闭式冷却水泵B出口阀故障" Unit="" ParentKKS="4号机组闭式冷却水泵" Time="0" />
  <DevMonitorNode Id="3935" TagName="40PGA00AP002RP" Describe="闭式冷却水泵B启动位置" Unit="" ParentKKS="4号机组闭式冷却水泵" Time="0" />
  <DevMonitorNode Id="52741" TagName="40PGA00AP002RD" Describe="闭式冷却水泵B启动指令" Unit="" ParentKKS="4号机组闭式冷却水泵" Time="0" />
  <DevMonitorNode Id="52742" TagName="40PGA00AP002SE" Describe="闭式冷却水泵B弹簧已储能" Unit="" ParentKKS="4号机组闭式冷却水泵" Time="0" />
  <DevMonitorNode Id="52737" TagName="40PGA00AP002LP" Describe="闭式冷却水泵B控制回路断线" Unit="" ParentKKS="4号机组闭式冷却水泵" Time="0" />
  <DevMonitorNode Id="52740" TagName="40PGA00AP002RC" Describe="闭式冷却水泵B远方位置" Unit="" ParentKKS="4号机组闭式冷却水泵" Time="0" />
  <DevMonitorNode Id="3420" TagName="40PGA00CP301" Describe="闭式冷却水泵出口母管压力" Unit="" ParentKKS="4号机组闭式冷却水泵" Time="0" />
  <DevMonitorNode Id="3421" TagName="40PGA00CT001" Describe="闭式冷却水泵出口母管温度" Unit="" ParentKKS="4号机组闭式冷却水泵" Time="0" />
  <DevMonitorNode Id="3418" TagName="40PGA00AP001I" Describe="闭式循环冷却水泵A电动机电流" Unit="" ParentKKS="4号机组闭式冷却水泵" Time="0" />
  <DevMonitorNode Id="3419" TagName="40PGA00AP002I" Describe="闭式循环冷却水泵B电动机电流" Unit="" ParentKKS="4号机组闭式冷却水泵" Time="0" />
</DevMonitorNodeList>